pure_validator/__init__.py
pure_validator/__main__.py
pure_validator/builtins.py
pure_validator/flake8_plugin.py
pure_validator/ir.py
pure_validator/ir_constructor.py
pure_validator/main.py
pure_validator/message.py
pure_validator/purity_checker.py
pure_validator/tests/__init__.py
pure_validator/tests/sources/01_simple.py
pure_validator/tests/sources/02_annotations.py
pure_validator/tests/sources/03_recursive.py
pure_validator/tests/sources/04_globals.py
pure_validator/tests/sources/__init__.py
pure_validator/tests/test_ir_loc.py
pure_validator/tests/test_sources.py
pure_validator-0.3.0.dist-info/WHEEL
pure_validator-0.3.0.dist-info/entry_points.txt
pure_validator-0.3.0.dist-info/METADATA
pure_validator-0.3.0.dist-info/RECORD
