Metadata-Version: 2.3
Name: pure-validator
Version: 0.3.0
Summary: Purity validator for Python code.
Author: Johan Dahlin
Author-email: Johan Dahlin <jdahlin@gmail.com>
License: MIT
Classifier: Development Status :: 3 - Alpha
Classifier: Intended Audience :: Developers
Classifier: License :: OSI Approved :: MIT License
Classifier: Programming Language :: Python :: 3
Classifier: Programming Language :: Python :: 3.12
Requires-Dist: ruff>=0.12.10 ; extra == 'dev'
Requires-Dist: flake8>=7.3.0 ; extra == 'flake8'
Requires-Python: >=3.12
Project-URL: Homepage, https://github.com/jdahlin/pure
Project-URL: Repository, https://github.com/jdahlin/pure
Provides-Extra: dev
Provides-Extra: flake8
